projen/__init__.py
projen/py.typed
projen/_jsii/__init__.py
projen/_jsii/projen@0.99.3.jsii.tgz
projen/awscdk/__init__.py
projen/build/__init__.py
projen/cdk/__init__.py
projen/cdk8s/__init__.py
projen/cdktf/__init__.py
projen/circleci/__init__.py
projen/github/__init__.py
projen/github/workflows/__init__.py
projen/gitlab/__init__.py
projen/java/__init__.py
projen/javascript/__init__.py
projen/javascript/biome_config/__init__.py
projen/python/__init__.py
projen/python/uv_config/__init__.py
projen/release/__init__.py
projen/typescript/__init__.py
projen/vscode/__init__.py
projen/web/__init__.py
projen-0.99.3.data/scripts/projen
projen-0.99.3.dist-info/LICENSE
projen-0.99.3.dist-info/METADATA
projen-0.99.3.dist-info/WHEEL
projen-0.99.3.dist-info/top_level.txt
projen-0.99.3.dist-info/RECORD
